nonebot_plugin_RePixivSearcher/MessageSegment_.py
nonebot_plugin_RePixivSearcher/__init__.py
nonebot_plugin_RePixivSearcher/account.py
nonebot_plugin_RePixivSearcher/config.py
nonebot_plugin_RePixivSearcher/get_header.py
nonebot_plugin_RePixivSearcher/search.py
nonebot_plugin_RePixivSearcher-1.3.0.dist-info/METADATA
nonebot_plugin_RePixivSearcher-1.3.0.dist-info/WHEEL
nonebot_plugin_RePixivSearcher-1.3.0.dist-info/license.txt
nonebot_plugin_RePixivSearcher-1.3.0.dist-info/top_level.txt
nonebot_plugin_RePixivSearcher-1.3.0.dist-info/RECORD
