Metadata-Version: 2.1
Name: nonebot-plugin-RePixivSearcher
Version: 1.3.0
Summary: 基于OneBot适配器的NoneBot2从Pixiv爬图的插件
Home-page: https://github.com/SkyDynamic/nonebot_plugin_RePixivSearcher
Author: Sky_Dynamic
Author-email: SkyDynamic@outlook.com
Keywords: pip,nonebot2,nonebot,nonebot_plugin
Platform: any
Classifier: Programming Language :: Python :: 3
Classifier: License :: OSI Approved :: MIT License
Classifier: Operating System :: OS Independent
Requires-Python: >=3.7.3
License-File: license.txt
Requires-Dist: nonebot2 (>=2.0.0b5)
Requires-Dist: requests (>=2.27.1)
